federated_fraud_detection-0.9.0.dist-info/METADATA
federated_fraud_detection-0.9.0.dist-info/WHEEL
federated_fraud_detection-0.9.0.dist-info/license_files/LICENSE
federated_fraud_detection/__init__.py
federated_fraud_detection/__init__.pyi
federated_fraud_detection/py.typed
federated_fraud_detection/federated_fraud_detection.pypy37-pp73-x86_64-linux-gnu.so
federated_fraud_detection-0.9.0.dist-info/RECORD
