Metadata-Version: 2.1
Name: federated-fraud-detection
Version: 0.9.0
Classifier: Programming Language :: Rust
Classifier: Programming Language :: Python :: Implementation :: CPython
Classifier: Programming Language :: Python :: Implementation :: PyPy
License-File: LICENSE
Summary: WIP: Elliptic curve-based protocol for checking transactions' consistency among multiple banks.
Author: Jelle Vos
License: MIT
Requires-Python: >=3.7
